krivaja_calc/__init__.py
krivaja_calc/module_1.py
krivaja_calc/module_2.py
krivaja_calc-0.2.0.dist-info/METADATA
krivaja_calc-0.2.0.dist-info/WHEEL
krivaja_calc-0.2.0.dist-info/entry_points.txt
krivaja_calc-0.2.0.dist-info/RECORD
