Metadata-Version: 2.4
Name: krivaja_calc
Version: 0.2.0
Summary: it is simple calculator
Author-email: bogoljub <bob.stankovic@gov.ab.ca>
Requires-Python: >=3.10
Requires-Dist: twine>=6.2.0
